{
  "db_name": "PostgreSQL",
  "query": "\n        UPDATE incidents \n        SET title = COALESCE($2, title),\n            description = COALESCE($3, description),\n            severity = COALESCE($4, severity),\n            status = COALESCE($5, status),\n            root_cause = COALESCE($6, root_cause),\n            assigned_to = COALESCE($7, assigned_to),\n            resolved_at = CASE \n                WHEN $5 = 'resolved' AND resolved_at IS NULL \n                THEN NOW() \n                ELSE resolved_at \n            END,\n            updated_at = NOW()\n        WHERE id = $1\n        RETURNING id, title, description, \n                 severity, status, \n                 started_at, resolved_at, root_cause, \n                 created_by, assigned_to, created_at, updated_at\n        ",
  "describe": {
    "columns": [
      {
        "ordinal": 0,
        "name": "id",
        "type_info": "Uuid"
      },
      {
        "ordinal": 1,
        "name": "title",
        "type_info": "Text"
      },
      {
        "ordinal": 2,
        "name": "description",
        "type_info": "Text"
      },
      {
        "ordinal": 3,
        "name": "severity",
        "type_info": "Text"
      },
      {
        "ordinal": 4,
        "name": "status",
        "type_info": "Text"
      },
      {
        "ordinal": 5,
        "name": "started_at",
        "type_info": "Timestamptz"
      },
      {
        "ordinal": 6,
        "name": "resolved_at",
        "type_info": "Timestamptz"
      },
      {
        "ordinal": 7,
        "name": "root_cause",
        "type_info": "Text"
      },
      {
        "ordinal": 8,
        "name": "created_by",
        "type_info": "Uuid"
      },
      {
        "ordinal": 9,
        "name": "assigned_to",
        "type_info": "Uuid"
      },
      {
        "ordinal": 10,
        "name": "created_at",
        "type_info": "Timestamptz"
      },
      {
        "ordinal": 11,
        "name": "updated_at",
        "type_info": "Timestamptz"
      }
    ],
    "parameters": {
      "Left": [
        "Uuid",
        "Text",
        "Text",
        "Text",
        "Text",
        "Text",
        "Uuid"
      ]
    },
    "nullable": [
      false,
      false,
      true,
      false,
      false,
      false,
      true,
      true,
      true,
      true,
      false,
      false
    ]
  },
  "hash": "303d41c181fae2b5f07baf2a8759b94ad965ebfc105b7285da69ae68891fe1bb"
}
