{
  "db_name": "PostgreSQL",
  "query": "INSERT INTO testproducts (id, name, description, created_by, created_at, updated_at)\n         VALUES ($1, $2, $3, $4, $5, $6)\n         RETURNING id, name, description, created_by, created_at, updated_at",
  "describe": {
    "columns": [
      {
        "ordinal": 0,
        "name": "id",
        "type_info": "Uuid"
      },
      {
        "ordinal": 1,
        "name": "name",
        "type_info": "Text"
      },
      {
        "ordinal": 2,
        "name": "description",
        "type_info": "Text"
      },
      {
        "ordinal": 3,
        "name": "created_by",
        "type_info": "Uuid"
      },
      {
        "ordinal": 4,
        "name": "created_at",
        "type_info": "Timestamptz"
      },
      {
        "ordinal": 5,
        "name": "updated_at",
        "type_info": "Timestamptz"
      }
    ],
    "parameters": {
      "Left": [
        "Uuid",
        "Text",
        "Text",
        "Uuid",
        "Timestamptz",
        "Timestamptz"
      ]
    },
    "nullable": [
      false,
      false,
      true,
      false,
      false,
      false
    ]
  },
  "hash": "3013ada4835021cc31d5750432a80a952cb1a0d820153139226715a5802962cb"
}
