{
  "db_name": "PostgreSQL",
  "query": "SELECT id, name, description, status as \"status: TestproductsStatus\", priority, metadata, created_by, created_at, updated_at \n               FROM testproducts \n               ORDER BY created_at DESC \n               LIMIT $1 OFFSET $2",
  "describe": {
    "columns": [
      {
        "ordinal": 0,
        "name": "id",
        "type_info": "Uuid"
      },
      {
        "ordinal": 1,
        "name": "name",
        "type_info": "Text"
      },
      {
        "ordinal": 2,
        "name": "description",
        "type_info": "Text"
      },
      {
        "ordinal": 3,
        "name": "status: TestproductsStatus",
        "type_info": {
          "Custom": {
            "name": "testproducts_status",
            "kind": {
              "Enum": [
                "active",
                "inactive",
                "pending",
                "archived"
              ]
            }
          }
        }
      },
      {
        "ordinal": 4,
        "name": "priority",
        "type_info": "Int4"
      },
      {
        "ordinal": 5,
        "name": "metadata",
        "type_info": "Jsonb"
      },
      {
        "ordinal": 6,
        "name": "created_by",
        "type_info": "Uuid"
      },
      {
        "ordinal": 7,
        "name": "created_at",
        "type_info": "Timestamptz"
      },
      {
        "ordinal": 8,
        "name": "updated_at",
        "type_info": "Timestamptz"
      }
    ],
    "parameters": {
      "Left": [
        "Int8",
        "Int8"
      ]
    },
    "nullable": [
      false,
      false,
      true,
      false,
      false,
      false,
      false,
      false,
      false
    ]
  },
  "hash": "f4ef42881fd607c75dad137ea004d9a9ec2ada64084e63f4c91944f698c3c5a2"
}
